geode_explicit/__init__.py
geode_explicit/__init__.pyi
geode_explicit/brep_explicit.py
geode_explicit/brep_explicit.pyi
geode_explicit/py.typed
geode_explicit/section_explicit.py
geode_explicit/section_explicit.pyi
geode_explicit/bin/Geode-Explicit_brep.dll
geode_explicit/bin/Geode-Explicit_common.dll
geode_explicit/bin/Geode-Explicit_section.dll
geode_explicit/bin/__init__.pyi
geode_explicit/bin/geode_explicit_py_brep.cp311-win_amd64.pyd
geode_explicit/bin/geode_explicit_py_brep.pyi
geode_explicit/bin/geode_explicit_py_section.cp311-win_amd64.pyd
geode_explicit/bin/geode_explicit_py_section.pyi
geode_explicit-6.7.1.dist-info/METADATA
geode_explicit-6.7.1.dist-info/WHEEL
geode_explicit-6.7.1.dist-info/top_level.txt
geode_explicit-6.7.1.dist-info/RECORD
