Metadata-Version: 2.4
Name: Geode-Explicit
Version: 6.7.1
Summary: Geode-solutions OpenGeode module for building explicit models
Author-email: Geode-solutions <contact@geode-solutions.com>
License: Proprietary
Requires-Python: <3.13,>=3.9
Requires-Dist: geode-background==9.*,>=9.9.0
Requires-Dist: geode-common==33.*,>=33.15.0
Requires-Dist: geode-conversion==6.*,>=6.5.9
Requires-Dist: opengeode-core==15.*,>=15.30.13
Requires-Dist: opengeode-inspector==6.*,>=6.8.13
